LinguAligner/__init__.py
LinguAligner/aligners.py
LinguAligner/multiple_translations.py
LinguAligner/translation.py
LinguAligner/utils.py
lingualigner-1.0.7.dist-info/LICENSE
lingualigner-1.0.7.dist-info/WHEEL
lingualigner-1.0.7.dist-info/METADATA
lingualigner-1.0.7.dist-info/RECORD
