Metadata-Version: 2.1
Name: LinguAligner
Version: 1.0.7
Summary: LinguAligner is a Python library for aligning annotations in parallel corpora. It is designed to be used in the context of parallel corpora annotation alignment, where the goal is to align annotations in the source language with annotations in the target language. 
Author-email: lfc <lfc@di.uminho.pt>
Classifier: License :: OSI Approved :: MIT License
Requires-Dist: transformers[torch]
Requires-Dist: spacy
Requires-Dist: deep_translator
Requires-Dist: deepl
Requires-Dist: requests
Requires-Dist: uuid
Requires-Dist: fuzzywuzzy
Project-URL: Homepage, https://github.com/lfcc1/LinguAligner
Project-URL: Issues, https://github.com/lfcc1/LinguAligner/issues
